form_guard/__init__.py
form_guard/guard.py
sara_form_gaurd-0.1.0.dist-info/licenses/LICENSE
sara_form_gaurd-0.1.0.dist-info/METADATA
sara_form_gaurd-0.1.0.dist-info/WHEEL
sara_form_gaurd-0.1.0.dist-info/top_level.txt
sara_form_gaurd-0.1.0.dist-info/RECORD
