Metadata-Version: 2.4
Name: sara_form_gaurd
Version: 0.1.0
Summary: Prevent duplicate form submission within a cooldown period
Author-email: "Md. Shamim Miah" <shamim520386@gmail.com>
License: MIT
Requires-Python: >=3.12.3
License-File: LICENSE
Dynamic: license-file
